tkinter_dndr/__init__.py
tkinter_dndr/test_dndr.py
tkinter_dndr/tkinter_dndr.py
tkinter_dndr-0.0.6.dist-info/LICENSE
tkinter_dndr-0.0.6.dist-info/METADATA
tkinter_dndr-0.0.6.dist-info/WHEEL
tkinter_dndr-0.0.6.dist-info/top_level.txt
tkinter_dndr-0.0.6.dist-info/RECORD
