Metadata-Version: 2.1
Name: tkinter_dndr
Version: 0.0.6
Summary: A package that provides drag/drop and widget resize support directly on a GUI window
Home-page: https://github.com/the-pythonist/tkinter_dndr
Author: Samuel Amogbonjaye
Project-URL: Bug Tracker, https://github.com/the-pythonist/tkinter_dndr/issues
Classifier: Programming Language :: Python :: 3
Classifier: License :: OSI Approved :: MIT License
Classifier: Operating System :: OS Independent
Requires-Python: >=3.5
License-File: LICENSE
